mopidy_pummeluff/__init__.py
mopidy_pummeluff/ext.conf
mopidy_pummeluff/frontend.py
mopidy_pummeluff/registry.py
mopidy_pummeluff/sound.py
mopidy_pummeluff/web.py
mopidy_pummeluff/actions/__init__.py
mopidy_pummeluff/actions/base.py
mopidy_pummeluff/actions/playback.py
mopidy_pummeluff/actions/shutdown.py
mopidy_pummeluff/actions/tracklist.py
mopidy_pummeluff/actions/volume.py
mopidy_pummeluff/sounds/fail.wav
mopidy_pummeluff/sounds/success.wav
mopidy_pummeluff/threads/__init__.py
mopidy_pummeluff/threads/gpio_handler.py
mopidy_pummeluff/threads/tag_reader.py
mopidy_pummeluff/webui/index.html
mopidy_pummeluff/webui/script.js
mopidy_pummeluff/webui/style.css
Mopidy_Pummeluff-3.0.0.dist-info/LICENSE
Mopidy_Pummeluff-3.0.0.dist-info/METADATA
Mopidy_Pummeluff-3.0.0.dist-info/WHEEL
Mopidy_Pummeluff-3.0.0.dist-info/entry_points.txt
Mopidy_Pummeluff-3.0.0.dist-info/top_level.txt
Mopidy_Pummeluff-3.0.0.dist-info/RECORD
