Metadata-Version: 2.1
Name: Mopidy-Pummeluff
Version: 3.0.0
Summary: Pummeluff is a Mopidy extension which allows you to control Mopidy via RFID tags
Home-page: https://github.com/confirm/mopidy-pummeluff
Author: confirm IT solutions
Author-email: mopidy-pummeluff@confirm.ch
License: MIT
Platform: UNKNOWN
Classifier: Environment :: No Input/Output (Daemon)
Classifier: Intended Audience :: End Users/Desktop
Classifier: License :: OSI Approved :: MIT License
Classifier: Operating System :: OS Independent
Classifier: Programming Language :: Python :: 2
Classifier: Topic :: Multimedia :: Sound/Audio :: Players
License-File: LICENSE
Requires-Dist: setuptools
Requires-Dist: Mopidy (>=3)
Requires-Dist: pi-rc522 (==2.2.1)
Provides-Extra: develop
Requires-Dist: isort ; extra == 'develop'
Requires-Dist: mopidy ; extra == 'develop'
Requires-Dist: pycodestyle ; extra == 'develop'
Requires-Dist: pylint ; extra == 'develop'
Requires-Dist: setuptools ; extra == 'develop'
Requires-Dist: setuptools-scm ; extra == 'develop'
Requires-Dist: wheel ; extra == 'develop'
